.gitignore
.travis.yml
CHANGES.txt
README.rst
curl.patch
setup.cfg
setup.py
docs/Makefile
docs/conf.py
docs/index.rst
docs/scripts.rst
docs/settings.rst
pyramid_amdjs/__init__.py
pyramid_amdjs/amd.py
pyramid_amdjs/amddebug.py
pyramid_amdjs/compat.py
pyramid_amdjs/handlebars.py
pyramid_amdjs/pstatic.py
pyramid_amdjs/require.py
pyramid_amdjs/script.py
pyramid_amdjs.egg-info/PKG-INFO
pyramid_amdjs.egg-info/SOURCES.txt
pyramid_amdjs.egg-info/dependency_links.txt
pyramid_amdjs.egg-info/entry_points.txt
pyramid_amdjs.egg-info/not-zip-safe
pyramid_amdjs.egg-info/requires.txt
pyramid_amdjs.egg-info/top_level.txt
pyramid_amdjs/node_modules/handlebars/.npmignore
pyramid_amdjs/node_modules/handlebars/LICENSE
pyramid_amdjs/node_modules/handlebars/README.markdown
pyramid_amdjs/node_modules/handlebars/package.json
pyramid_amdjs/node_modules/handlebars/bin/handlebars
pyramid_amdjs/node_modules/handlebars/lib/handlebars.js
pyramid_amdjs/node_modules/handlebars/lib/handlebars/base.js
pyramid_amdjs/node_modules/handlebars/lib/handlebars/runtime.js
pyramid_amdjs/node_modules/handlebars/lib/handlebars/utils.js
pyramid_amdjs/node_modules/handlebars/lib/handlebars/compiler/ast.js
pyramid_amdjs/node_modules/handlebars/lib/handlebars/compiler/base.js
pyramid_amdjs/node_modules/handlebars/lib/handlebars/compiler/compiler.js
pyramid_amdjs/node_modules/handlebars/lib/handlebars/compiler/index.js
pyramid_amdjs/node_modules/handlebars/lib/handlebars/compiler/parser.js
pyramid_amdjs/node_modules/handlebars/lib/handlebars/compiler/printer.js
pyramid_amdjs/node_modules/handlebars/lib/handlebars/compiler/visitor.js
pyramid_amdjs/node_modules/handlebars/node_modules/optimist/LICENSE
pyramid_amdjs/node_modules/handlebars/node_modules/optimist/README.markdown
pyramid_amdjs/node_modules/handlebars/node_modules/optimist/index.js
pyramid_amdjs/node_modules/handlebars/node_modules/optimist/package.json
pyramid_amdjs/node_modules/handlebars/node_modules/optimist/x.js
pyramid_amdjs/node_modules/handlebars/node_modules/optimist/node_modules/wordwrap/.npmignore
pyramid_amdjs/node_modules/handlebars/node_modules/optimist/node_modules/wordwrap/README.markdown
pyramid_amdjs/node_modules/handlebars/node_modules/optimist/node_modules/wordwrap/index.js
