Metadata-Version: 1.1
Name: pyramid-amdjs
Version: 0.5.4
Summary: Pyramid JS/CSS resource management with curl.js
Home-page: https://github.com/fafhrd91/pyramid_amdjs/
Author: Nikolay Kim
Author-email: fafhrd91@gmail.com
License: MIT
Platform: UNKNOWN
Classifier: License :: OSI Approved :: MIT License
Classifier: Intended Audience :: Developers
Classifier: Programming Language :: Python
Classifier: Programming Language :: Python :: 2.6
Classifier: Programming Language :: Python :: 2.7
Classifier: Programming Language :: Python :: 3.2
Classifier: Programming Language :: Python :: 3.3
Classifier: Programming Language :: Python :: Implementation :: CPython
Classifier: Framework :: Pyramid
Classifier: Topic :: Internet :: WWW/HTTP
Classifier: Topic :: Internet :: WWW/HTTP :: WSGI
